LICENSE
lefi/__init__.py
lefi/client.py
lefi/errors.py
lefi/exts/__init__.py
lefi/exts/commands/__init__.py
lefi/exts/commands/bot.py
lefi/exts/commands/core/__init__.py
lefi/exts/commands/core/command.py
lefi/exts/commands/core/context.py
lefi/exts/commands/core/converters.py
lefi/exts/commands/core/cooldowns.py
lefi/exts/commands/core/handler.py
lefi/exts/commands/core/parser.py
lefi/exts/commands/core/plugin.py
lefi/exts/commands/errors.py
lefi/exts/interactions/app.py
lefi/http.py
lefi/objects/__init__.py
lefi/objects/attachments.py
lefi/objects/audit_logs.py
lefi/objects/base.py
lefi/objects/channel.py
lefi/objects/components.py
lefi/objects/embed.py
lefi/objects/emoji.py
lefi/objects/enums.py
lefi/objects/files.py
lefi/objects/flags.py
lefi/objects/guild.py
lefi/objects/integration.py
lefi/objects/interactions/__init__.py
lefi/objects/interactions/command.py
lefi/objects/interactions/converters.py
lefi/objects/interactions/interaction.py
lefi/objects/interactions/parser.py
lefi/objects/invite.py
lefi/objects/member.py
lefi/objects/mentions.py
lefi/objects/message.py
lefi/objects/permissions.py
lefi/objects/role.py
lefi/objects/template.py
lefi/objects/threads.py
lefi/objects/user.py
lefi/py.typed
lefi/ratelimiter.py
lefi/state.py
lefi/utils/__init__.py
lefi/utils/image.py
lefi/utils/iterators.py
lefi/utils/missing.py
lefi/utils/payload.py
lefi/utils/search.py
lefi/utils/snowflake.py
lefi/voice/__init__.py
lefi/voice/_opus.py
lefi/voice/bin/COPYING
lefi/voice/bin/libopus-0.x64.dll
lefi/voice/bin/libopus-0.x86.dll
lefi/voice/client.py
lefi/voice/player.py
lefi/voice/protocol.py
lefi/voice/state.py
lefi/voice/wsclient.py
lefi/ws/__init__.py
lefi/ws/basews.py
lefi/ws/opcodes.py
lefi/ws/ratelimiter.py
lefi/ws/shard.py
lefi/ws/wsclient.py
lefi-0.2.4.dist-info/LICENSE
lefi-0.2.4.dist-info/WHEEL
lefi-0.2.4.dist-info/METADATA
lefi-0.2.4.dist-info/RECORD
