Metadata-Version: 2.1
Name: lefi
Version: 0.2.4
Summary: A discord API wrapper focused on clean code, and usability
Home-page: https://github.com/an-dyy/Lefi
License: MIT
Keywords: discord,discordbot,discordapi
Author: an-dyy
Author-email: andy.development@protonmail.com
Requires-Python: >=3.9,<4.0
Classifier: License :: OSI Approved :: MIT License
Classifier: Programming Language :: Python :: 3
Classifier: Programming Language :: Python :: 3.10
Classifier: Programming Language :: Python :: 3.9
Requires-Dist: PyNaCl (>=1.4.0,<2.0.0)
Requires-Dist: aiohttp (>=3.7.4,<4.0.0)
Project-URL: Documentation, https://lefi.readthedocs.io/en/latest/
